test_project
startcbv
