Metadata-Version: 1.0
Name: django-startcbv
Version: 0.2.3
Summary: Management command to start an app with class-based views.
Home-page: http://github.com/audreyr/django-startcbv
Author: Audrey Roy
Author-email: audreyr@gmail.com
License: MIT
Keywords: django
Platform: UNKNOWN
Classifier: Development Status :: 2 - Pre-Alpha
Classifier: Environment :: Web Environment
Classifier: Framework :: Django
Classifier: License :: OSI Approved :: BSD License
Classifier: Operating System :: OS Independent
Classifier: Programming Language :: JavaScript
Classifier: Programming Language :: Python :: 2.6
Classifier: Programming Language :: Python :: 2.7
Classifier: Topic :: Internet :: WWW/HTTP
Classifier: Topic :: Internet :: WWW/HTTP :: Dynamic Content
Classifier: Topic :: Software Development :: Libraries :: Python Modules
